hotbits/__init__.py
hotbits/__main__.py
hotbits-1.0.1.dist-info/LICENSE
hotbits-1.0.1.dist-info/METADATA
hotbits-1.0.1.dist-info/WHEEL
hotbits-1.0.1.dist-info/entry_points.txt
hotbits-1.0.1.dist-info/top_level.txt
hotbits-1.0.1.dist-info/RECORD
