Metadata-Version: 2.1
Name: hotbits
Version: 1.0.1
Summary: Python API for HotBits random data generator
Home-page: https://github.com/filips123/HotBitsPy/
Author: Filip Š
Author-email: projects@filips.si
License: GPLv3+
Keywords: random-generator,true-random,hotbits,api,generator
Platform: UNKNOWN
Classifier: Development Status :: 5 - Production/Stable
Classifier: Intended Audience :: Education
Classifier: Intended Audience :: Science/Research
Classifier: License :: OSI Approved :: GNU General Public License v3 or later (GPLv3+)
Classifier: Programming Language :: Python :: 3
Classifier: Topic :: Scientific/Engineering :: Mathematics
Classifier: Topic :: Scientific/Engineering :: Physics
Classifier: Topic :: Security :: Cryptography
Requires-Python: >= 3.4
Provides-Extra: lint
Requires-Dist: pylint ; extra == 'lint'
